d2spy/__init__.py
d2spy/api_client.py
d2spy/auth.py
d2spy/extras/__init__.py
d2spy/extras/third_party/__init__.py
d2spy/extras/third_party/tusclient/__init__.py
d2spy/extras/third_party/tusclient/client.py
d2spy/extras/third_party/tusclient/exceptions.py
d2spy/extras/third_party/tusclient/py.typed
d2spy/extras/third_party/tusclient/request.py
d2spy/extras/third_party/tusclient/uploader/__init__.py
d2spy/extras/third_party/tusclient/uploader/baseuploader.py
d2spy/extras/third_party/tusclient/uploader/uploader.py
d2spy/extras/utils.py
d2spy/models/__init__.py
d2spy/models/data_product.py
d2spy/models/data_product_collection.py
d2spy/models/flight.py
d2spy/models/flight_collection.py
d2spy/models/job.py
d2spy/models/location.py
d2spy/models/project.py
d2spy/models/project_collection.py
d2spy/models/raw_data.py
d2spy/models/user.py
d2spy/schemas/__init__.py
d2spy/schemas/data_product.py
d2spy/schemas/flight.py
d2spy/schemas/geojson.py
d2spy/schemas/project.py
d2spy/schemas/raw_data.py
d2spy/schemas/session.py
d2spy/schemas/stac_properties.py
d2spy/utils/logging_config.py
d2spy/workspace.py
d2spy-0.3.1.dist-info/LICENSE
d2spy-0.3.1.dist-info/METADATA
d2spy-0.3.1.dist-info/WHEEL
d2spy-0.3.1.dist-info/RECORD
