Metadata-Version: 2.3
Name: d2spy
Version: 0.3.1
Summary: Python package for interacting with a Data to Science instance.
License: MIT
Keywords: python,data to science,uas
Author: Ben Hancock
Author-email: hancocb@purdue.edu
Requires-Python: >=3.9,<4.0
Classifier: Development Status :: 3 - Alpha
Classifier: Intended Audience :: Science/Research
Classifier: License :: OSI Approved :: MIT License
Classifier: Operating System :: OS Independent
Classifier: Programming Language :: Python :: 3
Classifier: Programming Language :: Python :: 3.9
Classifier: Programming Language :: Python :: 3.10
Classifier: Programming Language :: Python :: 3.11
Classifier: Programming Language :: Python :: 3.12
Classifier: Programming Language :: Python :: 3.13
Requires-Dist: exifread (>=3.0.0,<4.0.0)
Requires-Dist: geojson-pydantic (>=1.1.1,<2.0.0)
Requires-Dist: geopandas (>=1.0.1,<2.0.0)
Requires-Dist: rasterio (>=1.3.11,<2.0.0)
Requires-Dist: requests (>=2.31.0,<3.0.0)
